setup.py
qamasu/__init__.py
qamasu/models.py
qamasu/tests.py
qamasu/views.py
qamasu.egg-info/PKG-INFO
qamasu.egg-info/SOURCES.txt
qamasu.egg-info/dependency_links.txt
qamasu.egg-info/requires.txt
qamasu.egg-info/top_level.txt
qamasu.egg-info/zip-safe