Metadata-Version: 1.1
Name: qamasu
Version: 0.5
Summary: Qamasu is Job Queue system that respects TheSchwartz.
Home-page: http://bitbucket.org/tsuyukimakoto/qamasu
Author: makoto tsuyuki
Author-email: mtsuyuki@gmail.com
License: New BSD
Keywords: queue,job,django,distributed
Platform: UNKNOWN
Classifier: Development Status :: 4 - Beta
Classifier: Framework :: Django
Classifier: Intended Audience :: Developers
Classifier: License :: OSI Approved :: BSD License
Classifier: Operating System :: OS Independent
Classifier: Programming Language :: Python :: 2.6
Classifier: Programming Language :: Python :: 2.7
Classifier: Programming Language :: Python :: 3.2
Classifier: Programming Language :: Python :: 3.3
Classifier: Topic :: System :: Distributed Computing
